LICENSE
README.md
setup.cfg
setup.py
GmoCoin.egg-info/PKG-INFO
GmoCoin.egg-info/SOURCES.txt
GmoCoin.egg-info/dependency_links.txt
GmoCoin.egg-info/requires.txt
GmoCoin.egg-info/top_level.txt
gmocoin/__init__.py
gmocoin/common/__init__.py
gmocoin/common/annotation.py
gmocoin/common/const.py
gmocoin/common/dto.py
gmocoin/common/exception.py
gmocoin/common/logging.py
gmocoin/private/__init__.py
gmocoin/private/api.py
gmocoin/private/dto.py
gmocoin/public/__init__.py
gmocoin/public/api.py
gmocoin/public/dto.py