Metadata-Version: 2.1
Name: GmoCoin
Version: 0.0.12
Summary: GMO Coin Client
Home-page: https://github.com/amashita/GmoCoin
Author: amashita
License: Apache License 2.0
Platform: UNKNOWN
